<annotation>
	<folder>train</folder>
	<filename>chicken breast (36).jpg</filename>
	<path>C:\Users\Joskillz\Documents\GitHub\images\train\chicken breast (36).jpg</path>
	<source>
		<database>Unknown</database>
	</source>
	<size>
		<width>300</width>
		<height>300</height>
		<depth>3</depth>
	</size>
	<segmented>0</segmented>
	<object>
		<name>chicken breast_brain food</name>
		<pose>Unspecified</pose>
		<truncated>0</truncated>
		<difficult>0</difficult>
		<bndbox>
			<xmin>59</xmin>
			<ymin>218</ymin>
			<xmax>164</xmax>
			<ymax>267</ymax>
		</bndbox>
	</object>
	<object>
		<name>chicken breast_brain food</name>
		<pose>Unspecified</pose>
		<truncated>0</truncated>
		<difficult>0</difficult>
		<bndbox>
			<xmin>75</xmin>
			<ymin>151</ymin>
			<xmax>155</xmax>
			<ymax>203</ymax>
		</bndbox>
	</object>
	<object>
		<name>chicken breast_brain food</name>
		<pose>Unspecified</pose>
		<truncated>0</truncated>
		<difficult>0</difficult>
		<bndbox>
			<xmin>75</xmin>
			<ymin>85</ymin>
			<xmax>160</xmax>
			<ymax>129</ymax>
		</bndbox>
	</object>
	<object>
		<name>chicken breast_brain food</name>
		<pose>Unspecified</pose>
		<truncated>0</truncated>
		<difficult>0</difficult>
		<bndbox>
			<xmin>180</xmin>
			<ymin>59</ymin>
			<xmax>241</xmax>
			<ymax>132</ymax>
		</bndbox>
	</object>
	<object>
		<name>chicken breast_brain food</name>
		<pose>Unspecified</pose>
		<truncated>0</truncated>
		<difficult>0</difficult>
		<bndbox>
			<xmin>185</xmin>
			<ymin>151</ymin>
			<xmax>238</xmax>
			<ymax>238</ymax>
		</bndbox>
	</object>
</annotation>
